first_glance/__init__.py
first_glance/report.py
first_glance-1.0.1.dist-info/METADATA
first_glance-1.0.1.dist-info/WHEEL
first_glance-1.0.1.dist-info/top_level.txt
first_glance-1.0.1.dist-info/RECORD
